aplicacion_ventas_by_darwin-0.1.0.dist-info/licenses/Licence
modulo_ventas/__init__.py
modulo_ventas/descuentos.py
modulo_ventas/exceptions.py
modulo_ventas/gestor_ventas.py
modulo_ventas/impuestos.py
modulo_ventas/precios.py
tests/__init__.py
tests/test_gestor_ventas.py
aplicacion_ventas_by_darwin-0.1.0.dist-info/METADATA
aplicacion_ventas_by_darwin-0.1.0.dist-info/WHEEL
aplicacion_ventas_by_darwin-0.1.0.dist-info/top_level.txt
aplicacion_ventas_by_darwin-0.1.0.dist-info/RECORD
